[{"CURRENCY":"CURRENCY","INDICES":"INDICES","BID":"BID","ASK":"ASK","Mid_Rate":"Mid Rate","BID_1":"BID","ASK_1":"ASK","Mid_Rate_1":"Mid Rate"},{"CURRENCY":"","INDICES":"","BID":"","ASK":"","Mid_Rate":"","BID_1":"ZiG","ASK_1":"ZiG","Mid_Rate_1":"ZiG"},{"CURRENCY":"INTERBANK RATE","INDICES":"","BID":"","ASK":"","Mid_Rate":"","BID_1":"","ASK_1":"","Mid_Rate_1":""},{"CURRENCY":"USD","INDICES":"","BID":"1","ASK":"1","Mid_Rate":"1 .0000","BID_1":"12.9771","ASK_1":"13.6425","Mid_Rate_1":"13.3098"},{"CURRENCY":"","INDICES":"","BID":"","ASK":"","Mid_Rate":"","BID_1":"","ASK_1":"","Mid_Rate_1":""},{"CURRENCY":"ZAR","INDICES":"","BID":"18.1868","ASK":"18.1958","Mid_Rate":"1 8.19130","BID_1":"1.3330","ASK_1":"1.4021","Mid_Rate_1":"1.3676"},{"CURRENCY":"GBP","INDICES":"*","BID":"1.2708","ASK":"1.2713","Mid_Rate":"1 .27105","BID_1":"16.4912","ASK_1":"17.3437","Mid_Rate_1":"16.9175"},{"CURRENCY":"JPY","INDICES":"","BID":"156.3600","ASK":"156.3700","Mid_Rate":"1 56.36500","BID_1":"11.4612","ASK_1":"12.0496","Mid_Rate_1":"11.7554"},{"CURRENCY":"ZMW\/ZMK","INDICES":"","BID":"25.8000","ASK":"25.8500","Mid_Rate":"2 5.82500","BID_1":"1.8911","ASK_1":"1.9919","Mid_Rate_1":"1.9415"},{"CURRENCY":"BWP","INDICES":"","BID":"0.0739","ASK":"0.0743","Mid_Rate":"0 .07410","BID_1":"0.9590","ASK_1":"1.0136","Mid_Rate_1":"0.9863"},{"CURRENCY":"CHF","INDICES":"","BID":"0.9103","ASK":"0.9108","Mid_Rate":"0 .91055","BID_1":"11.8130","ASK_1":"12.4255","Mid_Rate_1":"12.1193"},{"CURRENCY":"MWK","INDICES":"","BID":"1716.7300","ASK":"1750.0300","Mid_Rate":"1 ,733.38000","BID_1":"125.8369","ASK_1":"134.8552","Mid_Rate_1":"130.3461"},{"CURRENCY":"AUD","INDICES":"*","BID":"0.6657","ASK":"0.6659","Mid_Rate":"0 .66580","BID_1":"8.6388","ASK_1":"9.0845","Mid_Rate_1":"8.8617"},{"CURRENCY":"SDR","INDICES":"*","BID":"1.325400","ASK":"1.325400","Mid_Rate":"1 .32540","BID_1":"17.6408","ASK_1":"17.6408","Mid_Rate_1":"17.6408"},{"CURRENCY":"MZN\/MET","INDICES":"","BID":"63.2700","ASK":"64.0700","Mid_Rate":"6 3.67000","BID_1":"4.6377","ASK_1":"4.9371","Mid_Rate_1":"4.7874"},{"CURRENCY":"NOK","INDICES":"","BID":"10.7078","ASK":"10.7105","Mid_Rate":"1 0.70915","BID_1":"0.7848","ASK_1":"0.8253","Mid_Rate_1":"0.8051"},{"CURRENCY":"SEK","INDICES":"","BID":"10.6871","ASK":"10.6910","Mid_Rate":"1 0.68905","BID_1":"0.7833","ASK_1":"0.8238","Mid_Rate_1":"0.8036"},{"CURRENCY":"CAD","INDICES":"*","BID":"1.3634","ASK":"1.3638","Mid_Rate":"1 .36360","BID_1":"0.0999","ASK_1":"0.1050","Mid_Rate_1":"0.1025"},{"CURRENCY":"EUR","INDICES":"*","BID":"1.0859","ASK":"1.0860","Mid_Rate":"1 .08595","BID_1":"14.0918","ASK_1":"14.8157","Mid_Rate_1":"14.4538"},{"CURRENCY":"CNY","INDICES":"","BID":"7.2355","ASK":"7.2359","Mid_Rate":"7 .23570","BID_1":"0.5303","ASK_1":"0.5575","Mid_Rate_1":"0.5439"},{"CURRENCY":"INR","INDICES":"","BID":"83.3220","ASK":"83.3320","Mid_Rate":"8 3.32700","BID_1":"6.1075","ASK_1":"6.4214","Mid_Rate_1":"6.2645"},{"CURRENCY":"NZD","INDICES":"*","BID":"0.6098","ASK":"0.6101","Mid_Rate":"0 .60995","BID_1":"7.9134","ASK_1":"8.3232","Mid_Rate_1":"8.1183"},{"CURRENCY":"DKK","INDICES":"","BID":"6.8705","ASK":"6.8708","Mid_Rate":"6 .87065","BID_1":"0.5036","ASK_1":"0.5294","Mid_Rate_1":"0.5165"},{"CURRENCY":"XAU","INDICES":"","BID":"2413.8900","ASK":"2414.2000","Mid_Rate":"2,414.04500","BID_1":"31325.2919","ASK_1":"32935.7235","Mid_Rate_1":"32130.5077"},{"CURRENCY":"AFN","INDICES":"","BID":"71.7600","ASK":"71.9600","Mid_Rate":"7 1.86000","BID_1":"5.2600","ASK_1":"5.5451","Mid_Rate_1":"5.4026"},{"CURRENCY":"THB","INDICES":"","BID":"36.2800","ASK":"36.3100","Mid_Rate":"3 6.29500","BID_1":"2.6593","ASK_1":"2.7980","Mid_Rate_1":"2.7287"},{"CURRENCY":"ETB","INDICES":"","BID":"56.9985","ASK":"57.8903","Mid_Rate":"5 7.44440","BID_1":"4.1780","ASK_1":"4.4609","Mid_Rate_1":"4.3195"},{"CURRENCY":"SZL","INDICES":"","BID":"18.1870","ASK":"18.1920","Mid_Rate":"1 8.18950","BID_1":"1.3331","ASK_1":"1.4018","Mid_Rate_1":"1.3675"},{"CURRENCY":"MUR","INDICES":"","BID":"45.9900","ASK":"46.2900","Mid_Rate":"4 6.14000","BID_1":"3.3710","ASK_1":"3.5670","Mid_Rate_1":"3.4690"},{"CURRENCY":"MYR","INDICES":"","BID":"4.6900","ASK":"4.6930","Mid_Rate":"4 .69150","BID_1":"0.3437","ASK_1":"0.3616","Mid_Rate_1":"0.3527"},{"CURRENCY":"LSL","INDICES":"","BID":"18.1870","ASK":"18.1920","Mid_Rate":"1 8.18950","BID_1":"1.3331","ASK_1":"1.4018","Mid_Rate_1":"1.3675"},{"CURRENCY":"CYP","INDICES":"*","BID":"0.3975","ASK":"0.3980","Mid_Rate":"0 .39775","BID_1":"0.0291","ASK_1":"0.0306","Mid_Rate_1":"0.0299"},{"CURRENCY":"EGP","INDICES":"","BID":"46.6900","ASK":"46.7900","Mid_Rate":"4 6.74000","BID_1":"3.4223","ASK_1":"3.6055","Mid_Rate_1":"3.5139"},{"CURRENCY":"BRL","INDICES":"","BID":"5.1040","ASK":"5.1050","Mid_Rate":"5 .10450","BID_1":"0.3741","ASK_1":"0.3933","Mid_Rate_1":"0.3837"},{"CURRENCY":"TZS","INDICES":"","BID":"2590.0000","ASK":"2600.0000","Mid_Rate":"2,595.00000","BID_1":"189.8479","ASK_1":"200.3529","Mid_Rate_1":"195.1004"},{"CURRENCY":"RUB","INDICES":"","BID":"90.7200","ASK":"90.7400","Mid_Rate":"9 0.73000","BID_1":"6.6498","ASK_1":"6.9923","Mid_Rate_1":"6.8211"},{"CURRENCY":"KES","INDICES":"","BID":"131.0000","ASK":"132.0000","Mid_Rate":"1 31.50000","BID_1":"9.6023","ASK_1":"10.1717","Mid_Rate_1":"9.8870"},{"CURRENCY":"DEM","INDICES":"","BID":"2.2150","ASK":"2.2175","Mid_Rate":"2 .21625","BID_1":"0.1623","ASK_1":"0.1708","Mid_Rate_1":"0.1666"},{"CURRENCY":"ESP","INDICES":"","BID":"188.4300","ASK":"188.6500","Mid_Rate":"1 88.54000","BID_1":"13.8119","ASK_1":"14.5371","Mid_Rate_1":"14.1745"},{"CURRENCY":"ITL","INDICES":"","BID":"2192.8300","ASK":"2195.3200","Mid_Rate":"2,194.07500","BID_1":"160.7352","ASK_1":"169.1687","Mid_Rate_1":"164.9520"},{"CURRENCY":"FRF","INDICES":"","BID":"7.4287","ASK":"7.4372","Mid_Rate":"7 .43295","BID_1":"0.5445","ASK_1":"0.5731","Mid_Rate_1":"0.5588"},{"CURRENCY":"HKD","INDICES":"","BID":"7.7495","ASK":"7.8006","Mid_Rate":"7 .77505","BID_1":"0.5680","ASK_1":"0.6011","Mid_Rate_1":"0.5846"},{"CURRENCY":"ARS","INDICES":"","BID":"888.5000","ASK":"889.0000","Mid_Rate":"8 88.75000","BID_1":"65.1273","ASK_1":"68.5052","Mid_Rate_1":"66.8163"},{"CURRENCY":"XAF","INDICES":"","BID":"604.0700","ASK":"624.4900","Mid_Rate":"6 14.28000","BID_1":"44.2785","ASK_1":"48.1224","Mid_Rate_1":"46.2005"}]